contadorbcd.v
module contadorBCD(clock, valor, overflow, reset);
    output[3:0] valor;
    output overflow;
    reg[3:0] valor;
    reg overflow;
    input clock;
    input reset;

    always @(posedge clock or posedge reset) begin
        if(reset) begin
            valor = 0;
				overflow = 0;
        end else begin
			  valor = valor + 1;

			  if(valor==10) begin
					valor = 0;
					overflow = 1;
					overflow = 0;
			  end
		  end

    end

endmodule

urna.v
module urna(valid, estado, next_estado, clock, finish, confirma, reset, digit, digito1, digito2, digito3, digito4, candidatoArthur, candidatoLeandro, candidatoMateus, candidatoPablo, candidatoNulo, votoValido);

   input clock, valid, finish, confirma, reset;
   input[3:0] digit;


   output[3:0] digito1, digito2, digito3, digito4;
   output candidatoArthur, candidatoLeandro, candidatoMateus, candidatoPablo, candidatoNulo;
	 output[2:0] estado, next_estado;

    
    reg[3:0] digito1, digito2, digito3, digito4;
    reg[3:0] next_digito1, next_digito2, next_digito3, next_digito4;

    reg[2:0] estado;
    reg[2:0] next_estado;
     
    //Indica se o voto foi válido ou nulo
    output reg[1:0] votoValido;
    reg[1:0] next_votoValido;

    //Esses registradores servem para indicar para quem foi atribuido o voto
    reg candidatoArthur, candidatoLeandro, candidatoMateus, candidatoPablo, candidatoNulo;
    reg next_candidatoArthur, next_candidatoLeandro, next_candidatoMateus, next_candidatoPablo, next_candidatoNulo;
    
    //Matriculas em BCD para fins de comparação
    parameter matriculaArthur =  16'b0011010100000011;
    parameter matriculaLeandro = 16'b0011010100010011;
    parameter matriculaMateus =  16'b0011010010001001;
    parameter matriculaPablo  =  16'b0011010010000000;
    
    //estados
    parameter aguardando1Dig = 3'b000;
    parameter aguardando2Dig = 3'b001;
    parameter aguardando3Dig = 3'b010;
    parameter aguardando4Dig = 3'b011;
    parameter aguardandoConfirma = 3'b100;
	 parameter resetando = 3'b111;

    //Bloco always responsável pela mudança de estado
    always @(posedge clock) begin
        if(~finish) begin
            if(reset) begin
		
                candidatoArthur <= 0;
                candidatoLeandro <= 0;
                candidatoMateus <= 0;
                candidatoPablo <= 0;
                candidatoNulo <= 0;

                digito1 <= 0;
                digito2 <= 0;
                digito3 <= 0;
                digito4 <= 0;

                votoValido <= 0;
                estado <= resetando;

            end

            if(~reset) begin

                candidatoArthur <= next_candidatoArthur;
                candidatoLeandro <= next_candidatoLeandro;
                candidatoMateus <= next_candidatoMateus;
                candidatoPablo <= next_candidatoPablo;
                candidatoNulo <= next_candidatoNulo;
		
		//Atribui nos registradores principais os digitos inseridos pelo usuário
                digito1 <= next_digito1;
                digito2 <= next_digito2;
                digito3 <= next_digito3;
                digito4 <= next_digito4;

                votoValido <= next_votoValido;
                estado <= next_estado;

            end
        end
    end

    //Bloco always responsável por monitorar o input valid. Toda vez que o valid tem borda de subida igual a 1, uma nova ação (novo digito, confirma, reset ou corrige) por parte do usuário foi acionada.
    always @(posedge valid) begin

            case(estado)
		//Toda vez que a urna é resetada esse estado é acionado para resetar os registradores auxiliares
					 resetando: begin
						  next_estado<=aguardando1Dig;
              next_candidatoArthur <= 0;
              next_candidatoLeandro <= 0;
              next_candidatoMateus <= 0;
              next_candidatoPablo <= 0;
              next_candidatoNulo <= 0;

              next_digito1 <= 0;
              next_digito2 <= 0;
              next_digito3 <= 0;
              next_digito4 <= 0;
					 end
		//Além de zerar todos os registradores auxiliares também recebe o primeiro digito
                aguardando1Dig: begin
                    next_candidatoArthur <= 0;
                    next_candidatoLeandro <= 0;
                    next_candidatoMateus <= 0;
                    next_candidatoPablo <= 0;
                    next_candidatoNulo <= 0;


                    next_digito2 <= 0;
                    next_digito3 <= 0;
                    next_digito4 <= 0;
                    next_digito1 <= digit;

						  next_estado <= aguardando2Dig;
                end
		//Recebe o primeiro digito
                aguardando2Dig: begin
                    next_digito2 <= digit;
						  next_estado <= aguardando3Dig;
                end
		//Recebe o terceiro digito
                aguardando3Dig: begin
                    next_digito3 <= digit;
						  next_estado <= aguardando4Dig;
                end
		//Recebe o quarto digito
                aguardando4Dig: begin
                    next_digito4 <= digit;
						  next_estado <= aguardandoConfirma;
                end
		//Caso o confirma tenha sido pressionado ele contabiliza um voto para o candidato com número equivalente ao digitado. Caso o número não seja sememlhante ao de nenhum cadidato o voto é contabilizado comcomo nulo.
                aguardandoConfirma: begin
                    case({digito1, digito2, digito3, digito4})

                        matriculaArthur: begin
                            if(confirma) begin
                                next_candidatoArthur <= 1;
                                next_votoValido <=1;
										  next_estado <= aguardando1Dig;
                            end
                        end

                        matriculaLeandro: begin
                            if(confirma) begin
                                next_candidatoLeandro <= 1;
                                next_votoValido <=1;
										  next_estado <= aguardando1Dig;
                            end
                        end

                        matriculaMateus: begin
                            if(confirma) begin
                                next_candidatoMateus <= 1;
                                next_votoValido <=1;
										  next_estado <= aguardando1Dig;
                            end
                        end

                        matriculaPablo: begin
                            if(confirma) begin
                                next_candidatoPablo <= 1;
                                next_votoValido <=1;
										  next_estado <= aguardando1Dig;
                            end
                        end

                        default: begin
                            if(confirma) begin
                                next_candidatoNulo <= 1;
                                next_votoValido <=3;
										  next_estado <= aguardando1Dig;
                            end
                        end
                    endcase
                end
            endcase
    end


endmodule

clock1unit.v
module clock1unit(output clk);

reg clk;

initial begin
 clk = 0;
end

always begin
  #1 clk = ~clk;

end

endmodule

testbench.v
`include "urna.v"
`include "contadorbcd.v"
`include "clock1unit.v"

module testbench ();

      wire clock;
      wire candidatoArthur, candidatoMateus, candidatoPablo, candidatoNulo, candidatoLeandro,
	  bcdOver0_0_1, bcdOver0_1_2, bcdOver0_2_3, bcdOver0_3_4, bcdOver0_4_5,
	  bcdOver1_0_1, bcdOver1_1_2, bcdOver1_2_3, bcdOver1_3_4, bcdOver1_4_5,
	  bcdOver2_0_1, bcdOver2_1_2, bcdOver2_2_3, bcdOver2_3_4, bcdOver2_4_5,
	  bcdOver3_0_1, bcdOver3_1_2, bcdOver3_2_3, bcdOver3_3_4, bcdOver3_4_5,
	  bcdOver4_0_1, bcdOver4_1_2, bcdOver4_2_3, bcdOver4_3_4, bcdOver4_4_5;

    wire[3:0] digito1, digito2, digito3, digito4,
			 bcd0_0, bcd0_1, bcd0_2, bcd0_3, bcd0_4, bcd0_5,
			 bcd1_0, bcd1_1, bcd1_2, bcd1_3, bcd1_4, bcd1_5,
			 bcd2_0, bcd2_1, bcd2_2, bcd2_3, bcd2_4, bcd2_5,
			 bcd3_0, bcd3_1, bcd3_2, bcd3_3, bcd3_4, bcd3_5,
			 bcd4_0, bcd4_1, bcd4_2, bcd4_3, bcd4_4, bcd4_5,
			 bcd5_0, bcd5_1, bcd5_2, bcd5_3, bcd5_4, bcd5_5,
			 bcdo0, bcdo1, bcdo2, bcdo3, bcdo4, bcdo5, bcdo6, bcdo7;

    wire[2:0] estado, next_estado;
    wire[1:0] votoValido;
    reg[3:0] digitar;
    reg valid, reset, confirma, resetUrna, finish;

      clock1unit clock0 (.clk(clock));

      urna urna0 (.clock(clock), .digit(digitar), .valid(valid), .confirma(confirma), .finish(finish), .reset(resetUrna), .next_estado(next_estado), .candidatoArthur(candidatoArthur), .estado(estado),
      				.candidatoPablo(candidatoPablo), .candidatoMateus(candidatoMateus), .candidatoNulo(candidatoNulo), .candidatoLeandro(candidatoLeandro), .digito1(digito1), .digito2(digito2), .digito3(digito3),
      				.digito4(digito4), .votoValido(votoValido));

      contadorBCD bcdModule0_0 (.clock(candidatoArthur), .valor(bcd0_0), .overflow(bcdOver0_0_1), .reset(reset));
      contadorBCD bcdModule0_1 (.clock(bcdOver0_0_1), .valor(bcd0_1), .overflow(bcdOver0_1_2), .reset(reset));
      contadorBCD bcdModule0_2 (.clock(bcdOver0_1_2), .valor(bcd0_2), .overflow(bcdOver0_2_3), .reset(reset));
      contadorBCD bcdModule0_3 (.clock(bcdOver0_2_3), .valor(bcd0_3), .overflow(bcdOver0_3_4), .reset(reset));
      contadorBCD bcdModule0_4 (.clock(bcdOver0_3_4), .valor(bcd0_4), .overflow(bcdOver0_4_5), .reset(reset));
      contadorBCD bcdModule0_5 (.clock(bcdOver0_4_5), .valor(bcd0_5), .overflow(), .reset(reset));

      contadorBCD bcdModule1_0 (.clock(candidatoLeandro), .valor(bcd1_0), .overflow(bcdOver1_0_1), .reset(reset));
      contadorBCD bcdModule1_1 (.clock(bcdOver1_0_1), .valor(bcd1_1), .overflow(bcdOver1_1_2), .reset(reset));
      contadorBCD bcdModule1_2 (.clock(bcdOver1_1_2), .valor(bcd1_2), .overflow(bcdOver1_2_3), .reset(reset));
      contadorBCD bcdModule1_3 (.clock(bcdOver1_2_3), .valor(bcd1_3), .overflow(bcdOver1_3_4), .reset(reset));
      contadorBCD bcdModule1_4 (.clock(bcdOver1_3_4), .valor(bcd1_4), .overflow(bcdOver1_4_5), .reset(reset));
      contadorBCD bcdModule1_5 (.clock(bcdOver1_4_5), .valor(bcd1_5), .overflow(), .reset(reset));

      contadorBCD bcdModule2_0 (.clock(candidatoMateus), .valor(bcd2_0), .overflow(bcdOver2_0_1), .reset(reset));
      contadorBCD bcdModule2_1 (.clock(bcdOver2_0_1), .valor(bcd2_1), .overflow(bcdOver2_1_2), .reset(reset));
      contadorBCD bcdModule2_2 (.clock(bcdOver2_1_2), .valor(bcd2_2), .overflow(bcdOver2_2_3), .reset(reset));
      contadorBCD bcdModule2_3 (.clock(bcdOver2_2_3), .valor(bcd2_3), .overflow(bcdOver2_3_4), .reset(reset));
      contadorBCD bcdModule2_4 (.clock(bcdOver2_3_4), .valor(bcd2_4), .overflow(bcdOver2_4_5), .reset(reset));
      contadorBCD bcdModule2_5 (.clock(bcdOver2_4_5), .valor(bcd2_5), .overflow(), .reset(reset));

      contadorBCD bcdModule3_0 (.clock(candidatoPablo), .valor(bcd3_0), .overflow(bcdOver3_0_1), .reset(reset));
      contadorBCD bcdModule3_1 (.clock(bcdOver3_0_1), .valor(bcd3_1), .overflow(bcdOver3_1_2), .reset(reset));
      contadorBCD bcdModule3_2 (.clock(bcdOver3_1_2), .valor(bcd3_2), .overflow(bcdOver3_2_3), .reset(reset));
      contadorBCD bcdModule3_3 (.clock(bcdOver3_2_3), .valor(bcd3_3), .overflow(bcdOver3_3_4), .reset(reset));
      contadorBCD bcdModule3_4 (.clock(bcdOver3_3_4), .valor(bcd3_4), .overflow(bcdOver3_4_5), .reset(reset));
      contadorBCD bcdModule3_5 (.clock(bcdOver3_4_5), .valor(bcd3_5), .overflow(), .reset(reset));

      contadorBCD bcdModule4_0 (.clock(candidatoNulo), .valor(bcd4_0), .overflow(bcdOver4_0_1), .reset(reset));
      contadorBCD bcdModule4_1 (.clock(bcdOver4_0_1), .valor(bcd4_1), .overflow(bcdOver4_1_2), .reset(reset));
      contadorBCD bcdModule4_2 (.clock(bcdOver4_1_2), .valor(bcd4_2), .overflow(bcdOver4_2_3), .reset(reset));
      contadorBCD bcdModule4_3 (.clock(bcdOver4_2_3), .valor(bcd4_3), .overflow(bcdOver4_3_4), .reset(reset));
      contadorBCD bcdModule4_4 (.clock(bcdOver4_3_4), .valor(bcd4_4), .overflow(bcdOver4_4_5), .reset(reset));
      contadorBCD bcdModule4_5 (.clock(bcdOver4_4_5), .valor(bcd4_5), .overflow(), .reset(reset));

      initial begin
            $dumpfile("urnaEletronica.vcd");
            $dumpvars(0, testbench);

            reset = 0; confirma = 0; valid = 0; digitar = 0; resetUrna = 0; finish = 0; #20;
            resetUrna = 1; reset = 1; #20; valid = 1; #20; valid = 0; #20; resetUrna = 0; reset = 0; #20;

            digitar = 3; #20; valid = 1; #20; valid = 0; #20;
            digitar = 4; #20; valid = 1; #20; valid = 0; #20;
            digitar = 8; #20; valid = 1; #20; valid = 0; #20;
            digitar = 0; #20; valid = 1; #20; valid = 0; #20;
            confirma = 1; #20; valid = 1; #20; valid = 0; #20;

            $finish;

end

endmodule

urnaEletronica.vcd
$date
	Sun Dec 02 21:34:51 2018
$end
$version
	Icarus Verilog
$end
$timescale
	1s
$end
$scope module testbench $end
$var wire 2 ! votoValido [1:0] $end
$var wire 3 " next_estado [2:0] $end
$var wire 3 # estado [2:0] $end
$var wire 4 $ digito4 [3:0] $end
$var wire 4 % digito3 [3:0] $end
$var wire 4 & digito2 [3:0] $end
$var wire 4 ' digito1 [3:0] $end
$var wire 1 ( clock $end
$var wire 1 ) candidatoPablo $end
$var wire 1 * candidatoNulo $end
$var wire 1 + candidatoMateus $end
$var wire 1 , candidatoLeandro $end
$var wire 1 - candidatoArthur $end
$var wire 1 . bcdOver4_4_5 $end
$var wire 1 / bcdOver4_3_4 $end
$var wire 1 0 bcdOver4_2_3 $end
$var wire 1 1 bcdOver4_1_2 $end
$var wire 1 2 bcdOver4_0_1 $end
$var wire 1 3 bcdOver3_4_5 $end
$var wire 1 4 bcdOver3_3_4 $end
$var wire 1 5 bcdOver3_2_3 $end
$var wire 1 6 bcdOver3_1_2 $end
$var wire 1 7 bcdOver3_0_1 $end
$var wire 1 8 bcdOver2_4_5 $end
$var wire 1 9 bcdOver2_3_4 $end
$var wire 1 : bcdOver2_2_3 $end
$var wire 1 ; bcdOver2_1_2 $end
$var wire 1 < bcdOver2_0_1 $end
$var wire 1 = bcdOver1_4_5 $end
$var wire 1 > bcdOver1_3_4 $end
$var wire 1 ? bcdOver1_2_3 $end
$var wire 1 @ bcdOver1_1_2 $end
$var wire 1 A bcdOver1_0_1 $end
$var wire 1 B bcdOver0_4_5 $end
$var wire 1 C bcdOver0_3_4 $end
$var wire 1 D bcdOver0_2_3 $end
$var wire 1 E bcdOver0_1_2 $end
$var wire 1 F bcdOver0_0_1 $end
$var wire 4 G bcd4_5 [3:0] $end
$var wire 4 H bcd4_4 [3:0] $end
$var wire 4 I bcd4_3 [3:0] $end
$var wire 4 J bcd4_2 [3:0] $end
$var wire 4 K bcd4_1 [3:0] $end
$var wire 4 L bcd4_0 [3:0] $end
$var wire 4 M bcd3_5 [3:0] $end
$var wire 4 N bcd3_4 [3:0] $end
$var wire 4 O bcd3_3 [3:0] $end
$var wire 4 P bcd3_2 [3:0] $end
$var wire 4 Q bcd3_1 [3:0] $end
$var wire 4 R bcd3_0 [3:0] $end
$var wire 4 S bcd2_5 [3:0] $end
$var wire 4 T bcd2_4 [3:0] $end
$var wire 4 U bcd2_3 [3:0] $end
$var wire 4 V bcd2_2 [3:0] $end
$var wire 4 W bcd2_1 [3:0] $end
$var wire 4 X bcd2_0 [3:0] $end
$var wire 4 Y bcd1_5 [3:0] $end
$var wire 4 Z bcd1_4 [3:0] $end
$var wire 4 [ bcd1_3 [3:0] $end
$var wire 4 \ bcd1_2 [3:0] $end
$var wire 4 ] bcd1_1 [3:0] $end
$var wire 4 ^ bcd1_0 [3:0] $end
$var wire 4 _ bcd0_5 [3:0] $end
$var wire 4 ` bcd0_4 [3:0] $end
$var wire 4 a bcd0_3 [3:0] $end
$var wire 4 b bcd0_2 [3:0] $end
$var wire 4 c bcd0_1 [3:0] $end
$var wire 4 d bcd0_0 [3:0] $end
$var reg 1 e confirma $end
$var reg 4 f digitar [3:0] $end
$var reg 1 g finish $end
$var reg 1 h reset $end
$var reg 1 i resetUrna $end
$var reg 1 j valid $end
$scope module bcdModule0_0 $end
$var wire 1 h reset $end
$var wire 1 - clock $end
$var reg 1 F overflow $end
$var reg 4 k valor [3:0] $end
$upscope $end
$scope module bcdModule0_1 $end
$var wire 1 F clock $end
$var wire 1 h reset $end
$var reg 1 E overflow $end
$var reg 4 l valor [3:0] $end
$upscope $end
$scope module bcdModule0_2 $end
$var wire 1 E clock $end
$var wire 1 h reset $end
$var reg 1 D overflow $end
$var reg 4 m valor [3:0] $end
$upscope $end
$scope module bcdModule0_3 $end
$var wire 1 D clock $end
$var wire 1 h reset $end
$var reg 1 C overflow $end
$var reg 4 n valor [3:0] $end
$upscope $end
$scope module bcdModule0_4 $end
$var wire 1 C clock $end
$var wire 1 h reset $end
$var reg 1 B overflow $end
$var reg 4 o valor [3:0] $end
$upscope $end
$scope module bcdModule0_5 $end
$var wire 1 B clock $end
$var wire 1 h reset $end
$var reg 1 p overflow $end
$var reg 4 q valor [3:0] $end
$upscope $end
$scope module bcdModule1_0 $end
$var wire 1 h reset $end
$var wire 1 , clock $end
$var reg 1 A overflow $end
$var reg 4 r valor [3:0] $end
$upscope $end
$scope module bcdModule1_1 $end
$var wire 1 A clock $end
$var wire 1 h reset $end
$var reg 1 @ overflow $end
$var reg 4 s valor [3:0] $end
$upscope $end
$scope module bcdModule1_2 $end
$var wire 1 @ clock $end
$var wire 1 h reset $end
$var reg 1 ? overflow $end
$var reg 4 t valor [3:0] $end
$upscope $end
$scope module bcdModule1_3 $end
$var wire 1 ? clock $end
$var wire 1 h reset $end
$var reg 1 > overflow $end
$var reg 4 u valor [3:0] $end
$upscope $end
$scope module bcdModule1_4 $end
$var wire 1 > clock $end
$var wire 1 h reset $end
$var reg 1 = overflow $end
$var reg 4 v valor [3:0] $end
$upscope $end
$scope module bcdModule1_5 $end
$var wire 1 = clock $end
$var wire 1 h reset $end
$var reg 1 w overflow $end
$var reg 4 x valor [3:0] $end
$upscope $end
$scope module bcdModule2_0 $end
$var wire 1 h reset $end
$var wire 1 + clock $end
$var reg 1 < overflow $end
$var reg 4 y valor [3:0] $end
$upscope $end
$scope module bcdModule2_1 $end
$var wire 1 < clock $end
$var wire 1 h reset $end
$var reg 1 ; overflow $end
$var reg 4 z valor [3:0] $end
$upscope $end
$scope module bcdModule2_2 $end
$var wire 1 ; clock $end
$var wire 1 h reset $end
$var reg 1 : overflow $end
$var reg 4 { valor [3:0] $end
$upscope $end
$scope module bcdModule2_3 $end
$var wire 1 : clock $end
$var wire 1 h reset $end
$var reg 1 9 overflow $end
$var reg 4 | valor [3:0] $end
$upscope $end
$scope module bcdModule2_4 $end
$var wire 1 9 clock $end
$var wire 1 h reset $end
$var reg 1 8 overflow $end
$var reg 4 } valor [3:0] $end
$upscope $end
$scope module bcdModule2_5 $end
$var wire 1 8 clock $end
$var wire 1 h reset $end
$var reg 1 ~ overflow $end
$var reg 4 !" valor [3:0] $end
$upscope $end
$scope module bcdModule3_0 $end
$var wire 1 h reset $end
$var wire 1 ) clock $end
$var reg 1 7 overflow $end
$var reg 4 "" valor [3:0] $end
$upscope $end
$scope module bcdModule3_1 $end
$var wire 1 7 clock $end
$var wire 1 h reset $end
$var reg 1 6 overflow $end
$var reg 4 #" valor [3:0] $end
$upscope $end
$scope module bcdModule3_2 $end
$var wire 1 6 clock $end
$var wire 1 h reset $end
$var reg 1 5 overflow $end
$var reg 4 $" valor [3:0] $end
$upscope $end
$scope module bcdModule3_3 $end
$var wire 1 5 clock $end
$var wire 1 h reset $end
$var reg 1 4 overflow $end
$var reg 4 %" valor [3:0] $end
$upscope $end
$scope module bcdModule3_4 $end
$var wire 1 4 clock $end
$var wire 1 h reset $end
$var reg 1 3 overflow $end
$var reg 4 &" valor [3:0] $end
$upscope $end
$scope module bcdModule3_5 $end
$var wire 1 3 clock $end
$var wire 1 h reset $end
$var reg 1 '" overflow $end
$var reg 4 (" valor [3:0] $end
$upscope $end
$scope module bcdModule4_0 $end
$var wire 1 h reset $end
$var wire 1 * clock $end
$var reg 1 2 overflow $end
$var reg 4 )" valor [3:0] $end
$upscope $end
$scope module bcdModule4_1 $end
$var wire 1 2 clock $end
$var wire 1 h reset $end
$var reg 1 1 overflow $end
$var reg 4 *" valor [3:0] $end
$upscope $end
$scope module bcdModule4_2 $end
$var wire 1 1 clock $end
$var wire 1 h reset $end
$var reg 1 0 overflow $end
$var reg 4 +" valor [3:0] $end
$upscope $end
$scope module bcdModule4_3 $end
$var wire 1 0 clock $end
$var wire 1 h reset $end
$var reg 1 / overflow $end
$var reg 4 ," valor [3:0] $end
$upscope $end
$scope module bcdModule4_4 $end
$var wire 1 / clock $end
$var wire 1 h reset $end
$var reg 1 . overflow $end
$var reg 4 -" valor [3:0] $end
$upscope $end
$scope module bcdModule4_5 $end
$var wire 1 . clock $end
$var wire 1 h reset $end
$var reg 1 ." overflow $end
$var reg 4 /" valor [3:0] $end
$upscope $end
$scope module clock0 $end
$var reg 1 ( clk $end
$upscope $end
$scope module urna0 $end
$var wire 1 ( clock $end
$var wire 1 e confirma $end
$var wire 4 0" digit [3:0] $end
$var wire 1 g finish $end
$var wire 1 i reset $end
$var wire 1 j valid $end
$var reg 1 - candidatoArthur $end
$var reg 1 , candidatoLeandro $end
$var reg 1 + candidatoMateus $end
$var reg 1 * candidatoNulo $end
$var reg 1 ) candidatoPablo $end
$var reg 4 1" digito1 [3:0] $end
$var reg 4 2" digito2 [3:0] $end
$var reg 4 3" digito3 [3:0] $end
$var reg 4 4" digito4 [3:0] $end
$var reg 3 5" estado [2:0] $end
$var reg 1 6" next_candidatoArthur $end
$var reg 1 7" next_candidatoLeandro $end
$var reg 1 8" next_candidatoMateus $end
$var reg 1 9" next_candidatoNulo $end
$var reg 1 :" next_candidatoPablo $end
$var reg 4 ;" next_digito1 [3:0] $end
$var reg 4 <" next_digito2 [3:0] $end
$var reg 4 =" next_digito3 [3:0] $end
$var reg 4 >" next_digito4 [3:0] $end
$var reg 3 ?" next_estado [2:0] $end
$var reg 2 @" next_votoValido [1:0] $end
$var reg 2 A" votoValido [1:0] $end
$upscope $end
$upscope $end
$enddefinitions $end
#0
$dumpvars
bx A"
bx @"
bx ?"
bx >"
bx ="
bx <"
bx ;"
x:"
x9"
x8"
x7"
x6"
bx 5"
bx 4"
bx 3"
bx 2"
bx 1"
b0 0"
bx /"
x."
bx -"
bx ,"
bx +"
bx *"
bx )"
bx ("
x'"
bx &"
bx %"
bx $"
bx #"
bx ""
bx !"
x~
bx }
bx |
bx {
bx z
bx y
bx x
xw
bx v
bx u
bx t
bx s
bx r
bx q
xp
bx o
bx n
bx m
bx l
bx k
0j
0i
0h
0g
b0 f
0e
bx d
bx c
bx b
bx a
bx `
bx _
bx ^
bx ]
bx \
bx [
bx Z
bx Y
bx X
bx W
bx V
bx U
bx T
bx S
bx R
bx Q
bx P
bx O
bx N
bx M
bx L
bx K
bx J
bx I
bx H
bx G
xF
xE
xD
xC
xB
xA
x@
x?
x>
x=
x<
x;
x:
x9
x8
x7
x6
x5
x4
x3
x2
x1
x0
x/
x.
x-
x,
x+
x*
x)
0(
bx '
bx &
bx %
bx $
bx #
bx "
bx !
$end
#1
1(
#2
0(
#3
1(
#4
0(
#5
1(
#6
0(
#7
1(
#8
0(
#9
1(
#10
0(
#11
1(
#12
0(
#13
1(
#14
0(
#15
1(
#16
0(
#17
1(
#18
0(
#19
1(
#20
0F
b0 d
b0 k
0E
b0 c
b0 l
0D
b0 b
b0 m
0C
b0 a
b0 n
0B
b0 `
b0 o
0p
b0 _
b0 q
0A
b0 ^
b0 r
0@
b0 ]
b0 s
0?
b0 \
b0 t
0>
b0 [
b0 u
0=
b0 Z
b0 v
0w
b0 Y
b0 x
0<
b0 X
b0 y
0;
b0 W
b0 z
0:
b0 V
b0 {
09
b0 U
b0 |
08
b0 T
b0 }
0~
b0 S
b0 !"
07
b0 R
b0 ""
06
b0 Q
b0 #"
05
b0 P
b0 $"
04
b0 O
b0 %"
03
b0 N
b0 &"
0'"
b0 M
b0 ("
02
b0 L
b0 )"
01
b0 K
b0 *"
00
b0 J
b0 +"
0/
b0 I
b0 ,"
0.
b0 H
b0 -"
0."
b0 G
b0 /"
0(
1h
1i
#21
b111 #
b111 5"
b0 !
b0 A"
b0 $
b0 4"
b0 %
b0 3"
b0 &
b0 2"
b0 '
b0 1"
0*
0)
0+
0,
0-
1(
#22
0(
#23
1(
#24
0(
#25
1(
#26
0(
#27
1(
#28
0(
#29
1(
#30
0(
#31
1(
#32
0(
#33
1(
#34
0(
#35
1(
#36
0(
#37
1(
#38
0(
#39
1(
#40
b0 >"
b0 ="
b0 <"
b0 ;"
09"
0:"
08"
07"
06"
b0 "
b0 ?"
0(
1j
#41
1(
#42
0(
#43
1(
#44
0(
#45
1(
#46
0(
#47
1(
#48
0(
#49
1(
#50
0(
#51
1(
#52
0(
#53
1(
#54
0(
#55
1(
#56
0(
#57
1(
#58
0(
#59
1(
#60
0(
0j
#61
1(
#62
0(
#63
1(
#64
0(
#65
1(
#66
0(
#67
1(
#68
0(
#69
1(
#70
0(
#71
1(
#72
0(
#73
1(
#74
0(
#75
1(
#76
0(
#77
1(
#78
0(
#79
1(
#80
0(
0h
0i
#81
b0 #
b0 5"
bx !
bx A"
1(
#82
0(
#83
1(
#84
0(
#85
1(
#86
0(
#87
1(
#88
0(
#89
1(
#90
0(
#91
1(
#92
0(
#93
1(
#94
0(
#95
1(
#96
0(
#97
1(
#98
0(
#99
1(
#100
0(
b11 f
b11 0"
#101
1(
#102
0(
#103
1(
#104
0(
#105
1(
#106
0(
#107
1(
#108
0(
#109
1(
#110
0(
#111
1(
#112
0(
#113
1(
#114
0(
#115
1(
#116
0(
#117
1(
#118
0(
#119
1(
#120
b1 "
b1 ?"
b11 ;"
0(
1j
#121
b1 #
b1 5"
b11 '
b11 1"
1(
#122
0(
#123
1(
#124
0(
#125
1(
#126
0(
#127
1(
#128
0(
#129
1(
#130
0(
#131
1(
#132
0(
#133
1(
#134
0(
#135
1(
#136
0(
#137
1(
#138
0(
#139
1(
#140
0(
0j
#141
1(
#142
0(
#143
1(
#144
0(
#145
1(
#146
0(
#147
1(
#148
0(
#149
1(
#150
0(
#151
1(
#152
0(
#153
1(
#154
0(
#155
1(
#156
0(
#157
1(
#158
0(
#159
1(
#160
0(
b101 f
b101 0"
#161
1(
#162
0(
#163
1(
#164
0(
#165
1(
#166
0(
#167
1(
#168
0(
#169
1(
#170
0(
#171
1(
#172
0(
#173
1(
#174
0(
#175
1(
#176
0(
#177
1(
#178
0(
#179
1(
#180
b10 "
b10 ?"
b101 <"
0(
1j
#181
b10 #
b10 5"
b101 &
b101 2"
1(
#182
0(
#183
1(
#184
0(
#185
1(
#186
0(
#187
1(
#188
0(
#189
1(
#190
0(
#191
1(
#192
0(
#193
1(
#194
0(
#195
1(
#196
0(
#197
1(
#198
0(
#199
1(
#200
0(
0j
#201
1(
#202
0(
#203
1(
#204
0(
#205
1(
#206
0(
#207
1(
#208
0(
#209
1(
#210
0(
#211
1(
#212
0(
#213
1(
#214
0(
#215
1(
#216
0(
#217
1(
#218
0(
#219
1(
#220
0(
b0 f
b0 0"
#221
1(
#222
0(
#223
1(
#224
0(
#225
1(
#226
0(
#227
1(
#228
0(
#229
1(
#230
0(
#231
1(
#232
0(
#233
1(
#234
0(
#235
1(
#236
0(
#237
1(
#238
0(
#239
1(
#240
b11 "
b11 ?"
0(
1j
#241
b11 #
b11 5"
1(
#242
0(
#243
1(
#244
0(
#245
1(
#246
0(
#247
1(
#248
0(
#249
1(
#250
0(
#251
1(
#252
0(
#253
1(
#254
0(
#255
1(
#256
0(
#257
1(
#258
0(
#259
1(
#260
0(
0j
#261
1(
#262
0(
#263
1(
#264
0(
#265
1(
#266
0(
#267
1(
#268
0(
#269
1(
#270
0(
#271
1(
#272
0(
#273
1(
#274
0(
#275
1(
#276
0(
#277
1(
#278
0(
#279
1(
#280
0(
b11 f
b11 0"
#281
1(
#282
0(
#283
1(
#284
0(
#285
1(
#286
0(
#287
1(
#288
0(
#289
1(
#290
0(
#291
1(
#292
0(
#293
1(
#294
0(
#295
1(
#296
0(
#297
1(
#298
0(
#299
1(
#300
b100 "
b100 ?"
b11 >"
0(
1j
#301
b100 #
b100 5"
b11 $
b11 4"
1(
#302
0(
#303
1(
#304
0(
#305
1(
#306
0(
#307
1(
#308
0(
#309
1(
#310
0(
#311
1(
#312
0(
#313
1(
#314
0(
#315
1(
#316
0(
#317
1(
#318
0(
#319
1(
#320
0(
0j
#321
1(
#322
0(
#323
1(
#324
0(
#325
1(
#326
0(
#327
1(
#328
0(
#329
1(
#330
0(
#331
1(
#332
0(
#333
1(
#334
0(
#335
1(
#336
0(
#337
1(
#338
0(
#339
1(
#340
0(
1e
#341
1(
#342
0(
#343
1(
#344
0(
#345
1(
#346
0(
#347
1(
#348
0(
#349
1(
#350
0(
#351
1(
#352
0(
#353
1(
#354
0(
#355
1(
#356
0(
#357
1(
#358
0(
#359
1(
#360
b0 "
b0 ?"
b1 @"
16"
0(
1j
#361
b1 d
b1 k
b0 #
b0 5"
b1 !
b1 A"
1-
1(
#362
0(
#363
1(
#364
0(
#365
1(
#366
0(
#367
1(
#368
0(
#369
1(
#370
0(
#371
1(
#372
0(
#373
1(
#374
0(
#375
1(
#376
0(
#377
1(
#378
0(
#379
1(
#380
0(
0j
#381
1(
#382
0(
#383
1(
#384
0(
#385
1(
#386
0(
#387
1(
#388
0(
#389
1(
#390
0(
#391
1(
#392
0(
#393
1(
#394
0(
#395
1(
#396
0(
#397
1(
#398
0(
#399
1(
#400
0(
#401
1(
#402
0(
#403
1(
#404
0(
#405
1(
#406
0(
#407
1(
#408
0(
#409
1(
#410
0(
#411
1(
#412
0(
#413
1(
#414
0(
#415
1(
#416
0(
#417
1(
#418
0(
#419
1(
#420
b1 "
b1 ?"
b0 >"
b0 <"
06"
0(
1j
#421
b1 #
b1 5"
b0 $
b0 4"
b0 &
b0 2"
0-
1(
#422
0(
#423
1(
#424
0(
#425
1(
#426
0(
#427
1(
#428
0(
#429
1(
#430
0(
#431
1(
#432
0(
#433
1(
#434
0(
#435
1(
#436
0(
#437
1(
#438
0(
#439
1(
#440
0(
0j
#441
1(
#442
0(
#443
1(
#444
0(
#445
1(
#446
0(
#447
1(
#448
0(
#449
1(
#450
0(
#451
1(
#452
0(
#453
1(
#454
0(
#455
1(
#456
0(
#457
1(
#458
0(
#459
1(
#460
0(
b101 f
b101 0"
#461
1(
#462
0(
#463
1(
#464
0(
#465
1(
#466
0(
#467
1(
#468
0(
#469
1(
#470
0(
#471
1(
#472
0(
#473
1(
#474
0(
#475
1(
